cliboa/__init__.py
cliboa/adapter/__init__.py
cliboa/adapter/aws.py
cliboa/adapter/azure.py
cliboa/adapter/csv.py
cliboa/adapter/file.py
cliboa/adapter/ftp.py
cliboa/adapter/gcp.py
cliboa/adapter/http.py
cliboa/adapter/mysql.py
cliboa/adapter/postgres.py
cliboa/adapter/rdbms.py
cliboa/adapter/sftp.py
cliboa/adapter/sqlite.py
cliboa/cli/__init__.py
cliboa/cli/cliboadmin.py
cliboa/common/environment.py
cliboa/conf/__init__.py
cliboa/conf/cliboa.ini
cliboa/conf/default_environment.py
cliboa/conf/logging.conf
cliboa/core/__init__.py
cliboa/core/factory.py
cliboa/core/file_parser.py
cliboa/core/listener.py
cliboa/core/manager.py
cliboa/core/scenario_queue.py
cliboa/core/step_queue.py
cliboa/core/strategy.py
cliboa/core/validator.py
cliboa/core/worker.py
cliboa/interface.py
cliboa/scenario/__init__.py
cliboa/scenario/aws.py
cliboa/scenario/azure.py
cliboa/scenario/base.py
cliboa/scenario/extract/aws.py
cliboa/scenario/extract/azure.py
cliboa/scenario/extract/file.py
cliboa/scenario/extract/ftp.py
cliboa/scenario/extract/gcp.py
cliboa/scenario/extract/http.py
cliboa/scenario/extract/mysql.py
cliboa/scenario/extract/postgres.py
cliboa/scenario/extract/sftp.py
cliboa/scenario/extract/sqlite.py
cliboa/scenario/extras.py
cliboa/scenario/ftp.py
cliboa/scenario/gcp.py
cliboa/scenario/http.py
cliboa/scenario/load/aws.py
cliboa/scenario/load/azure.py
cliboa/scenario/load/file.py
cliboa/scenario/load/gcp.py
cliboa/scenario/load/http.py
cliboa/scenario/load/mysql.py
cliboa/scenario/load/postgres.py
cliboa/scenario/load/sftp.py
cliboa/scenario/load/sqlite.py
cliboa/scenario/rdbms.py
cliboa/scenario/sample_step.py
cliboa/scenario/sftp.py
cliboa/scenario/sqlite.py
cliboa/scenario/transform/aes.py
cliboa/scenario/transform/csv.py
cliboa/scenario/transform/file.py
cliboa/scenario/transform/gpg.py
cliboa/scenario/transform/json.py
cliboa/scenario/transform/system.py
cliboa/scenario/validator.py
cliboa/template/__init__.py
cliboa/template/bin/__init__.py
cliboa-2.7.1b0.dist-info/METADATA
cliboa-2.7.1b0.dist-info/WHEEL
cliboa-2.7.1b0.dist-info/entry_points.txt
cliboa-2.7.1b0.dist-info/licenses/LICENSE
cliboa-2.7.1b0.dist-info/RECORD
