Metadata-Version: 2.4
Name: cliboa
Version: 2.7.1b0
Summary: application framework for ETL(ELT) processing
License-Expression: MIT
License-File: LICENSE
Keywords: etl,elt,data pipeline,workflow,automation,framework
Author: BrainPad
Author-email: cliboa@brainpad.co.jp
Requires-Python: >=3.10,<4.0
Classifier: Development Status :: 4 - Beta
Classifier: Intended Audience :: Developers
Classifier: Topic :: Software Development :: Libraries :: Application Frameworks
Classifier: Programming Language :: Python :: 3.10
Classifier: Programming Language :: Python :: 3.11
Classifier: Programming Language :: Python :: 3.12
Requires-Dist: PyMySQL (>=1.0.2,<2.0.0)
Requires-Dist: PyYaml (>=6.0.2,<7.0.0)
Requires-Dist: azure-storage-blob (>=12.9.0,<13.0.0)
Requires-Dist: boto3 (>=1.20.16,<2.0.0)
Requires-Dist: chardet (>=4.0.0)
Requires-Dist: cloudpickle (>=2.0.0)
Requires-Dist: cryptography (>=44.0.1,<45.0.0)
Requires-Dist: dask (>=2025.7.0)
Requires-Dist: google-auth (>=2.3.3,<3.0.0)
Requires-Dist: google-cloud-bigquery (>=2.30.1)
Requires-Dist: google-cloud-firestore (>=2.3.4,<3.0.0)
Requires-Dist: google-cloud-storage (>=1.43.0)
Requires-Dist: jsonlines (>=2.0.0)
Requires-Dist: multiprocessing-logging (>=0.3.1,<0.4.0)
Requires-Dist: numpy (<2)
Requires-Dist: pandas (>=1.3.4)
Requires-Dist: paramiko (>=2.10.5)
Requires-Dist: psycopg2-binary (>=2.9.1,<3.0.0)
Requires-Dist: pyarrow (>=14.0.1)
Requires-Dist: python-dateutil (>=2.9.0,<3.0.0)
Requires-Dist: python-gnupg (>=0.5.4,<0.6.0)
Requires-Dist: requests (>=2.26.0,<3.0.0)
Project-URL: ChangeLog, https://github.com/BrainPad/cliboa/releases
Project-URL: Documentation, https://github.com/BrainPad/cliboa/wiki
Project-URL: Homepage, https://github.com/BrainPad/cliboa
Project-URL: Issues, https://github.com/BrainPad/cliboa/issues
Project-URL: Repository, https://github.com/BrainPad/cliboa
